fastcpd/BUILD.bazel
fastcpd/__init__.py
fastcpd/interface.cpython-310-darwin.so
fastcpd/py.typed
fastcpd/pybind.cc
fastcpd/segmentation.py
fastcpd/variance_estimation.py
fastcpd-0.18.0.dist-info/licenses/LICENSE.md
fastcpd-0.18.0.dist-info/METADATA
fastcpd-0.18.0.dist-info/WHEEL
fastcpd-0.18.0.dist-info/top_level.txt
fastcpd-0.18.0.dist-info/RECORD
