Metadata-Version: 2.4
Name: fastcpd
Version: 0.18.0
Summary: A Python package for performing fast change point detection.
Author-email: Xingchi Li <anthony.li.stat.tamu.edu@lixingchi.com>, Xianyang Zhang <zhangxiany@stat.tamu.edu>
Maintainer-email: Xingchi Li <anthony.li.stat.tamu.edu@lixingchi.com>
License-Expression: GPL-3.0-or-later
Project-URL: Documentation, https://fastcpd.xingchi.li/
Project-URL: Repository, https://github.com/doccstat/fastcpd
Classifier: Development Status :: 2 - Pre-Alpha
Classifier: Intended Audience :: Science/Research
Classifier: Operating System :: MacOS :: MacOS X
Classifier: Operating System :: Microsoft :: Windows
Classifier: Operating System :: POSIX
Classifier: Programming Language :: Python :: 3 :: Only
Classifier: Programming Language :: Python :: 3.10
Classifier: Programming Language :: Python :: 3.11
Classifier: Programming Language :: Python :: 3.12
Classifier: Programming Language :: R
Classifier: Programming Language :: C++
Classifier: Topic :: Scientific/Engineering
Classifier: Topic :: Scientific/Engineering :: Mathematics
Classifier: Topic :: Software Development :: Libraries
Requires-Python: >=3.10
License-File: LICENSE.md
Dynamic: license-file
